voxelfarm/AzureAuthClient.py
voxelfarm/__init__.py
voxelfarm/block_model.py
voxelfarm/function_lambda.py
voxelfarm/generator_lambda.py
voxelfarm/process_lambda.py
voxelfarm/report_lambda.py
voxelfarm/view_lambda.py
voxelfarm/voxelfarmclient.py
voxelfarm/workflow_lambda.py
voxelfarm-0.0.240.dist-info/LICENSE
voxelfarm-0.0.240.dist-info/METADATA
voxelfarm-0.0.240.dist-info/WHEEL
voxelfarm-0.0.240.dist-info/top_level.txt
voxelfarm-0.0.240.dist-info/RECORD
