Metadata-Version: 2.1
Name: voxelfarm
Version: 0.0.240
Summary: Voxel Farm Python Lambdas
Home-page: https://www.voxelfarm.com/help/PythonCookbook.html
Author: Voxel Farm
Author-email: webmaster@voxelfarm.com
License: UNKNOWN
Project-URL: Bug Tracker, https://github.com/voxelfarm/voxelfarmclient/issues
Platform: UNKNOWN
Classifier: Programming Language :: Python :: 3
Classifier: License :: OSI Approved :: MIT License
Classifier: Operating System :: OS Independent
Requires-Python: >=3.7
License-File: LICENSE
Requires-Dist: pandas
Requires-Dist: requests
Requires-Dist: pybase64
Requires-Dist: msal
Provides-Extra: dev
Requires-Dist: pytest>=3.7; extra == "dev"
